xpl/__init__.py
xpl/__main__.py
xpl/canvas_selection.py
xpl/datahandler.py
xpl/fileio.py
xpl/fitter.py
xpl/gui.py
xpl/menubar.ui
xpl/processing.py
xpl/rsf.db
xpl/view.py
xpl/xpl.glade
xpl/xpl.py
xpl/xpl_catalog.xml
xpl/assets/atom_lib.png
xpl/assets/logo.svg
xpl/assets/pan.png
xpl/assets/xpl.svg
xpl/assets/xpl48.png
xpl-0.8.6.2.data/data/share/applications/xpl.desktop
xpl-0.8.6.2.data/data/share/icons/xpl.svg
xpl-0.8.6.2.dist-info/LICENSE
xpl-0.8.6.2.dist-info/METADATA
xpl-0.8.6.2.dist-info/WHEEL
xpl-0.8.6.2.dist-info/top_level.txt
xpl-0.8.6.2.dist-info/RECORD
