Metadata-Version: 2.1
Name: xpl
Version: 0.8.6.2
Summary: XPS spectrum analysis
Home-page: https://github.com/schachmett/xpl
Author: Simon Fischer
License: GPLv3
Keywords: physics XPS x-ray photoelectron spectroscopy chemistry
Platform: UNKNOWN
Classifier: Programming Language :: Python :: 3
Classifier: Environment :: X11 Applications :: GTK
Classifier: License :: OSI Approved :: GNU General Public License v3 (GPLv3)
Classifier: Topic :: Scientific/Engineering :: Physics
Requires-Python: ~=3.5
Requires-Dist: matplotlib
Requires-Dist: numpy
Requires-Dist: cairocffi
Requires-Dist: lmfit
